Metadata-Version: 2.1
Name: model-maker
Version: 0.0.5
Summary: UNKNOWN
Home-page: https://github.com/shirecoding/ModelMaker
Author: shirecoding
Author-email: shirecoding@gmail.com
License: UNKNOWN
Download-URL: https://github.com/shirecoding/ModelMaker/archive/0.0.5.tar.gz
Platform: UNKNOWN
Classifier: Programming Language :: Python :: 3
Classifier: License :: OSI Approved :: MIT License
Classifier: Operating System :: OS Independent
